conta/__init__.py
conta/calcular_balanco.py
conta/exportar_pdf.py
conta/grafico.py
conta/registrar_transacao.py
conta-0.0.3.dist-info/METADATA
conta-0.0.3.dist-info/WHEEL
conta-0.0.3.dist-info/top_level.txt
conta-0.0.3.dist-info/RECORD
